embedding_as_service/__init__.py
embedding_as_service/utils.py
embedding_as_service/text/__init__.py
embedding_as_service/text/encode.py
embedding_as_service/text/albert/__init__.py
embedding_as_service/text/albert/tokenization.py
embedding_as_service/text/bert/__init__.py
embedding_as_service/text/elmo/__init__.py
embedding_as_service/text/fasttext/__init__.py
embedding_as_service/text/glove/__init__.py
embedding_as_service/text/ulmfit/__init__.py
embedding_as_service/text/ulmfit/model.py
embedding_as_service/text/ulmfit/custom_layers/__init__.py
embedding_as_service/text/ulmfit/custom_layers/qrnn.py
embedding_as_service/text/ulmfit/custom_layers/tied_embeddings.py
embedding_as_service/text/use/__init__.py
embedding_as_service/text/word2vec/__init__.py
embedding_as_service/text/xlnet/__init__.py
embedding_as_service/text/xlnet/config.py
embedding_as_service/text/xlnet/models/__init__.py
embedding_as_service/text/xlnet/models/classifier_utils.py
embedding_as_service/text/xlnet/models/data_utils.py
embedding_as_service/text/xlnet/models/function_builder.py
embedding_as_service/text/xlnet/models/gpu_utils.py
embedding_as_service/text/xlnet/models/model_utils.py
embedding_as_service/text/xlnet/models/modeling.py
embedding_as_service/text/xlnet/models/prepro_utils.py
embedding_as_service/text/xlnet/models/run_classifier.py
embedding_as_service/text/xlnet/models/run_race.py
embedding_as_service/text/xlnet/models/run_squad.py
embedding_as_service/text/xlnet/models/squad_utils.py
embedding_as_service/text/xlnet/models/tpu_estimator.py
embedding_as_service/text/xlnet/models/train.py
embedding_as_service/text/xlnet/models/train_gpu.py
embedding_as_service/text/xlnet/models/xlnet.py
embedding_as_service-3.1.2.dist-info/METADATA
embedding_as_service-3.1.2.dist-info/WHEEL
embedding_as_service-3.1.2.dist-info/entry_points.txt
embedding_as_service-3.1.2.dist-info/top_level.txt
embedding_as_service-3.1.2.dist-info/RECORD
