Metadata-Version: 2.1
Name: embedding-as-service
Version: 3.1.2
Summary: embedding-as-service: one-stop solution to encode sentence to vectors using various embedding methods
Home-page: https://github.com/amansrivastava17/embedding-as-service
Author: Aman Srivastava
Author-email: amans.rlx@gmail.com
License: UNKNOWN
Keywords: bert nlp tensorflow machine learning sentence encoding embedding serving albert glove word2vec
Platform: UNKNOWN
Classifier: Programming Language :: Python :: 3.6
Classifier: License :: OSI Approved :: MIT License
Classifier: Operating System :: OS Independent
Requires-Python: >=3.6
Requires-Dist: keras (==2.2.4)
Requires-Dist: tqdm (==4.32.2)
Requires-Dist: numpy (==1.16.4)
Requires-Dist: requests (==2.21.0)
Requires-Dist: bert-tensorflow (==1.0.1)
Requires-Dist: tensorflow-hub (==0.4.0)
Requires-Dist: smart-open (==6.2.0)
Requires-Dist: tensorflow (==1.15.2)
Requires-Dist: setuptools (>=41.0.0)
Requires-Dist: sentencepiece (==0.1.85)
Requires-Dist: zmq (==0.0.0)
